{
  "_fv": 33,
  "_type": "villagertrade",
  "definition": {
    "tradeEntries": [
      {
        "villagerProfession": {
          "value": "CLERIC"
        },
        "entries": [
          {
            "price1": {
              "value": "Items.NETHER_STAR"
            },
            "countPrice1": 1,
            "price2": {
              "value": "Items.NAUTILUS_SHELL"
            },
            "countPrice2": 3,
            "offer": {
              "value": "CUSTOM:Tropics"
            },
            "countOffer": 1,
            "level": 3,
            "maxTrades": 3,
            "xp": 5,
            "priceMultiplier": 0.05
          }
        ]
      }
    ]
  }
}