{
  "_fv": 33,
  "_type": "recipe",
  "definition": {
    "recipeType": "Crafting",
    "xpReward": 0.0,
    "cookingTime": 200,
    "recipeRetstackSize": 3,
    "group": "",
    "recipeShapeless": false,
    "recipeSlots": [
      {
        "value": "CUSTOM:CypressPlanks"
      },
      {
        "value": "CUSTOM:CypressPlanks"
      },
      {
        "value": "CUSTOM:CypressPlanks"
      },
      {
        "value": "CUSTOM:CypressPlanks"
      },
      {
        "value": "CUSTOM:CypressPlanks"
      },
      {
        "value": "CUSTOM:CypressPlanks"
      },
      {
        "value": ""
      },
      {
        "value": "Items.STICK"
      },
      {
        "value": ""
      }
    ],
    "recipeReturnStack": {
      "value": "Items.SIGN"
    },
    "name": "sign_recipe_oak",
    "namespace": "mod"
  }
}