{
  "_fv": 33,
  "_type": "tool",
  "definition": {
    "renderType": 0,
    "texture": "tropicstone_axe",
    "customModelName": "Normal",
    "name": "Southstone Axe",
    "specialInfo": [],
    "creativeTab": {
      "value": "CUSTOM:ArcheonCombatAndTools"
    },
    "toolType": "Axe",
    "harvestLevel": 2,
    "efficiency": 4.0,
    "attackSpeed": 1.0,
    "enchantability": 14,
    "damageVsEntity": 5.5,
    "usageCount": 250,
    "blocksAffected": [],
    "hasGlow": false,
    "repairItems": [
      {
        "value": "CUSTOM:Tropicstone"
      }
    ],
    "immuneToFire": false,
    "stayInGridWhenCrafting": false,
    "damageOnCrafting": false
  }
}